doublemetaphone-1.2.dist-info/RECORD
doublemetaphone-1.2.dist-info/WHEEL
doublemetaphone-1.2.dist-info/top_level.txt
doublemetaphone-1.2.dist-info/METADATA
doublemetaphone-1.2.dist-info/licenses/LICENSE
doublemetaphone/__init__.py
doublemetaphone/doublemetaphone.cpython-310-darwin.so
